pypkg_happyxhw/__init__.py
pypkg_happyxhw/main.py
pypkg_happyxhw/fsutils/__init__.py
pypkg_happyxhw/fsutils/listdir.py
pypkg_happyxhw/setup_logging/__init__.py
pypkg_happyxhw/setup_logging/config.yaml
pypkg_happyxhw/setup_logging/setup.py
pypkg_happyxhw-0.0.4.dist-info/METADATA
pypkg_happyxhw-0.0.4.dist-info/WHEEL
pypkg_happyxhw-0.0.4.dist-info/top_level.txt
pypkg_happyxhw-0.0.4.dist-info/RECORD
