Metadata-Version: 2.1
Name: pypkg-happyxhw
Version: 0.0.4
Summary: python useful package
Home-page: https://git.happyxhw.cn:8443/happyxhw/pypkg.git
Author: happyxhw
Author-email: happyxhw@outlook.com
Requires-Dist: coloredlogs
Requires-Dist: pyyaml
